mcp_meituan_ip/__init__.py
mcp_meituan_ip/server.py
mcp_meituan_ip-0.1.1.dist-info/METADATA
mcp_meituan_ip-0.1.1.dist-info/WHEEL
mcp_meituan_ip-0.1.1.dist-info/entry_points.txt
mcp_meituan_ip-0.1.1.dist-info/RECORD
