Metadata-Version: 2.4
Name: mcp-meituan-ip
Version: 0.1.1
Summary: 这是一个根据美团接口查询位置的mcp服务器
Author: 123
Requires-Python: >=3.11
Requires-Dist: fastapi>=0.115.12
Requires-Dist: mcp>=1.6.0
Requires-Dist: requests>=2.32.3
